singbox_converter/__init__.py
singbox_converter/constants.py
singbox_converter/core.py
singbox_converter/exceptions.py
singbox_converter/main.py
singbox_converter/providers-example.json
singbox_converter/tool.py
singbox_converter/config_template/config_template_groups_rule_set_tun.json
singbox_converter/config_template/config_template_groups_tun.json
singbox_converter/config_template/config_template_groups_v6_rule_set_tun.json
singbox_converter/config_template/config_template_groups_wechat_rule_set_tun.json
singbox_converter/config_template/config_template_no_groups_tun.json
singbox_converter/config_template/config_template_no_groups_tun_VN.json
singbox_converter/parsers/__init__.py
singbox_converter/parsers/base.py
singbox_converter/parsers/clash2base64.py
singbox_converter/parsers/http.py
singbox_converter/parsers/https.py
singbox_converter/parsers/hysteria.py
singbox_converter/parsers/hysteria2.py
singbox_converter/parsers/socks.py
singbox_converter/parsers/ss.py
singbox_converter/parsers/ssr.py
singbox_converter/parsers/trojan.py
singbox_converter/parsers/tuic.py
singbox_converter/parsers/vless.py
singbox_converter/parsers/vmess.py
singbox_converter/parsers/wg.py
pysingboxconverter-0.5.2.dev0.dist-info/METADATA
pysingboxconverter-0.5.2.dev0.dist-info/WHEEL
pysingboxconverter-0.5.2.dev0.dist-info/entry_points.txt
pysingboxconverter-0.5.2.dev0.dist-info/top_level.txt
pysingboxconverter-0.5.2.dev0.dist-info/zip-safe
pysingboxconverter-0.5.2.dev0.dist-info/RECORD
